FPGA/verifiedHBridge.v
//`timescale 1ns/100ps

/*
H-Bridge Controller with Flyback Protection
----------------------------------------
This module controls an H-bridge circuit for driving inductive loads with integrated
flyback protection and energy tracking.

Key Features:
- Bidirectional control (forward/reverse)
- Automatic flyback handling through high-side switches
- Energy tracking and safe direction switching
- Synchronous timing for switch transitions

Operating Principles:
1. Energy Management:
   - Tracks energy buildup in the coil during ON time
   - Manages discharge through flyback circuit
   - Prevents direction switching until sufficient energy discharge
   - Energy counters decrease during flyback cycles

2. Switch Configuration:
   - Q1/Q3: High-side switches
   - Q2/Q4: Low-side switches
   - Forward operation: Q1+Q4
   - Reverse operation: Q3+Q2
   - Flyback path: Q1+Q3 (both high-side)

Timing Relationships:
1. Switch Transitions:
   - OutVGS activation: 0.5 clock after input signal (negedge after posedge)
   - FlybackVGS activation: Immediate on input signal removal
   - OutVGS deactivation: 0.5 clock after FlybackVGS activation
   NOTE: These timings may need adjustment based on MOSFET characteristics
         during physical testing to optimize voltage stability

2. Direction Changes:
   - Requires complete energy discharge via flyback
   - Enforces discharge time equal to previous ON time
   - Blocked direction changes don't interrupt flyback counting

Limitations and Requirements:
1. Frequency Limits:
   - Verified operation: >3 clock cycles (4MHz at 12MHz clock)
   - Recommended: >12 clock cycles (<1MHz switching at 12MHz clock)
   - Flyback energy tracking may be incomplete at highest frequencies

2. Reset State:
   - Both high-side switches active (Q1+Q3)
   - Both low-side switches inactive (Q2+Q4)

Usage Notes:
- InVGSf/InVGSr should not be active simultaneously
- For reliable operation, maintain switching frequency below 1MHz
- Energy tracking ensures safe direction changes
- Flyback counting continues during blocked direction attempts
*/

module hbridge_controller (
    input wire clk,                // 12MHz clock input
    input wire rst_n,              // Active-low reset
    input wire InVGSf,             // Forward drive input (>12 clocks recommended)
    input wire InVGSr,             // Reverse drive input (>12 clocks recommended)
    output reg Q1_out,             // High side forward switch
    output reg Q2_out,             // Low side reverse switch
    output reg Q3_out,             // High side reverse switch
    output reg Q4_out              // Low side forward switch
);

// Internal control signals
reg OutVGSf, OutVGSr;             // Drive set controls
reg FlybackVGS;                    // Flyback control
reg rising_edge_detected;          // Flag to track DriveSet rising edge
reg falling_edge_detected;         // Flag to track falling edge for sequencing

// Counter registers
reg [15:0] fwd_on_counter;        // Counts how long forward was on
reg [15:0] rev_on_counter;        // Counts how long reverse was on
reg [15:0] flyback_counter;       // Counts current flyback duration
reg last_dir_forward;             // Tracks which direction was last active
reg in_flyback_mode;              // Indicates we're in flyback waiting period
reg direction_blocked;            // Indicates direction change is blocked

// Handle positive edge of clock - FlybackVGS control and edge detection
always @(posedge clk or negedge rst_n) begin
    if (!rst_n) begin
        FlybackVGS <= 1;           // Default state is high (both high side on)
        rising_edge_detected <= 0;
        falling_edge_detected <= 0;
        fwd_on_counter <= 0;
        rev_on_counter <= 0;
        flyback_counter <= 0;
        in_flyback_mode <= 0;
        direction_blocked <= 0;
    end else begin
        // Counter logic for active states
        if (OutVGSf && InVGSf) begin
            fwd_on_counter <= fwd_on_counter + 1;
        end else if (OutVGSr && InVGSr) begin
            rev_on_counter <= rev_on_counter + 1;
        end

        // Flyback counting logic and energy discharge tracking
        if (FlybackVGS && in_flyback_mode && !OutVGSf && !OutVGSr) begin
            flyback_counter <= flyback_counter + 1;
            
            // Decrease the relevant counter based on last direction
            if (last_dir_forward && fwd_on_counter > 0) begin
                fwd_on_counter <= fwd_on_counter - 1;
            end else if (!last_dir_forward && rev_on_counter > 0) begin
                rev_on_counter <= rev_on_counter - 1;
            end
            
            // Check if we've fully discharged
            if ((last_dir_forward && fwd_on_counter <= 1) ||
                (!last_dir_forward && rev_on_counter <= 1)) begin
                direction_blocked <= 0;  // Unblock direction changes
                in_flyback_mode <= 0;    // Exit flyback mode
                fwd_on_counter <= 0;     // Reset counters after discharge
                rev_on_counter <= 0;
                flyback_counter <= 0;
            end
        end

        // Main control logic
        if (InVGSf || InVGSr) begin
            if (!rising_edge_detected) begin
                // New drive input detected
                if ((InVGSf && !last_dir_forward && in_flyback_mode) ||
                    (InVGSr && last_dir_forward && in_flyback_mode)) begin
                    // Attempting opposite direction during flyback
                    if ((last_dir_forward && fwd_on_counter < flyback_counter) ||
                        (!last_dir_forward && rev_on_counter < flyback_counter)) begin
                        direction_blocked <= 1;
                    end
                end else begin
                    // Same direction or flyback complete
                    FlybackVGS <= 0;
                    rising_edge_detected <= 1;
                    falling_edge_detected <= 0;
                    in_flyback_mode <= 0;
                    flyback_counter <= 0;
                    direction_blocked <= 0;
                    if (!in_flyback_mode) begin
                        // Reset the inactive direction's counter
                        if (InVGSf) begin
                            rev_on_counter <= 0;
                        end else begin
                            fwd_on_counter <= 0;
                        end
                    end
                end
            end
        end else begin  // Both inputs are low
            rising_edge_detected <= 0;
            if (OutVGSf || OutVGSr) begin
                // Drive set is active, start turn-off sequence
                FlybackVGS <= 1;
                falling_edge_detected <= 1;
                in_flyback_mode <= 1;
                flyback_counter <= 0;
            end else if (!FlybackVGS && !falling_edge_detected) begin
                // Short pulse case
                FlybackVGS <= 1;
                falling_edge_detected <= 0;
            end
        end
    end
end

// Handle negative edge of clock - DriveSet control
always @(negedge clk or negedge rst_n) begin
    if (!rst_n) begin
        OutVGSf <= 0;
        OutVGSr <= 0;
        last_dir_forward <= 0;     // Reset direction tracking
    end else begin
        if (rising_edge_detected && !direction_blocked) begin
            if (InVGSf) begin
                OutVGSf <= 1;
                OutVGSr <= 0;
                last_dir_forward <= 1;  // Update only on successful activation
            end else if (InVGSr) begin
                OutVGSf <= 0;
                OutVGSr <= 1;
                last_dir_forward <= 0;  // Update only on successful activation
            end
        end else if (falling_edge_detected || direction_blocked) begin
            OutVGSf <= 0;
            OutVGSr <= 0;
            // Direction state maintained during flyback
        end
    end
end

// Final switch output control
always @(*) begin
    // High side switches (Q1 and Q3)
    Q1_out = OutVGSf || FlybackVGS;
    Q3_out = OutVGSr || FlybackVGS;
    
    // Low side switches (Q2 and Q4)
    Q2_out = OutVGSr;
    Q4_out = OutVGSf;
end

endmodule

FPGA/verifiedHBridge_tb.v
`timescale 1ns/100ps

module hbridge_controller_tb;

// Testbench signals
reg clk;
reg rst_n;
reg InVGSf;
reg InVGSr;
wire Q1_out, Q2_out, Q3_out, Q4_out;

// Testbench-only signals for MOSFET set monitoring
wire TB_FWD_SET;
wire TB_REV_SET;

// Instantiate the H-bridge controller
hbridge_controller uut (
    .clk(clk),
    .rst_n(rst_n),
    .InVGSf(InVGSf),
    .InVGSr(InVGSr),
    .Q1_out(Q1_out),
    .Q2_out(Q2_out),
    .Q3_out(Q3_out),
    .Q4_out(Q4_out)
);

assign TB_FWD_SET = Q1_out && Q4_out;
assign TB_REV_SET = Q3_out && Q2_out;

// Clock generation
initial begin
    clk = 0;
    forever #41.667 clk = ~clk;  // 12MHz clock
end

// Task for Forward PWM testing
task test_forward_pwm;
    input integer on_cycles;
    input integer off_cycles;
    input integer repeat_count;
    begin
        $display("\nTesting Forward PWM: on=%0d, off=%0d, repeat=%0d", 
                 on_cycles, off_cycles, repeat_count);
        repeat(repeat_count) begin
            InVGSf = 1;
            repeat(on_cycles) @(posedge clk);
            InVGSf = 0;
            repeat(off_cycles) @(posedge clk);
        end
    end
endtask

// Task for Reverse PWM testing
task test_reverse_pwm;
    input integer on_cycles;
    input integer off_cycles;
    input integer repeat_count;
    begin
        $display("\nTesting Reverse PWM: on=%0d, off=%0d, repeat=%0d", 
                 on_cycles, off_cycles, repeat_count);
        repeat(repeat_count) begin
            InVGSr = 1;
            repeat(on_cycles) @(posedge clk);
            InVGSr = 0;
            repeat(off_cycles) @(posedge clk);
        end
    end
endtask

// Task for testing direction change
task test_direction_change;
    input integer first_dir_cycles;
    input integer wait_cycles;
    input integer second_dir_cycles;
    input integer start_forward;
    begin
        $display("\nDirection Change Test:");
        $display("First direction cycles: %0d", first_dir_cycles);
        $display("Wait cycles: %0d", wait_cycles);
        $display("Second direction cycles: %0d", second_dir_cycles);
        
        if (start_forward) begin
            InVGSf = 1;
            repeat(first_dir_cycles) @(posedge clk);
            InVGSf = 0;
            repeat(wait_cycles) @(posedge clk);
            InVGSr = 1;
            repeat(second_dir_cycles) @(posedge clk);
            InVGSr = 0;
        end else begin
            InVGSr = 1;
            repeat(first_dir_cycles) @(posedge clk);
            InVGSr = 0;
            repeat(wait_cycles) @(posedge clk);
            InVGSf = 1;
            repeat(second_dir_cycles) @(posedge clk);
            InVGSf = 0;
        end
        repeat(50) @(posedge clk);  // Additional settling time
    end
endtask

// Test stimulus
initial begin
    $dumpfile("hbridge_test.vcd");
    $dumpvars(0, hbridge_controller_tb);
    
    // Initialize inputs
    rst_n = 0;
    InVGSf = 0;
    InVGSr = 0;
    
    // Reset sequence
    #100;
    rst_n = 1;
    #100;

    // SECTION 1: Forward Direction Tests
    $display("\n=== FORWARD DIRECTION TESTS ===");
    
    // Long pulses
    test_forward_pwm(30, 30, 3);  // 30 clock cycles on/off
    #200;
    
    // Medium pulses
    test_forward_pwm(15, 15, 5);  // 15 clock cycles on/off
    #200;
    
    // Short pulses
    test_forward_pwm(5, 5, 10);   // 5 clock cycles on/off
    #200;
    
    // Very short pulses
    test_forward_pwm(2, 2, 15);   // 2 clock cycles on/off
    #200;
    
    // Single clock pulses
    test_forward_pwm(1, 1, 20);   // 1 clock cycle on/off
    #300;

    // SECTION 2: Reverse Direction Tests
    $display("\n=== REVERSE DIRECTION TESTS ===");
    
    // Long pulses
    test_reverse_pwm(30, 30, 3);
    #200;
    
    // Medium pulses
    test_reverse_pwm(15, 15, 5);
    #200;
    
    // Short pulses
    test_reverse_pwm(5, 5, 10);
    #200;
    
    // Very short pulses
    test_reverse_pwm(2, 2, 15);
    #200;
    
    // Single clock pulses
    test_reverse_pwm(1, 1, 20);
    #300;

    // SECTION 3: Direction Change Tests
    $display("\n=== DIRECTION CHANGE TESTS ===");
    
    // Test Case 1: Long ON with insufficient wait (should block)
    test_direction_change(30, 15, 30, 1);
    #500;
    
    // Test Case 2: Long ON with sufficient wait (should allow)
    test_direction_change(30, 35, 30, 1);
    #500;
    
    // Test Case 3: Medium ON with insufficient wait (should block)
    test_direction_change(15, 7, 15, 0);
    #500;
    
    // Test Case 4: Medium ON with sufficient wait (should allow)
    test_direction_change(15, 20, 15, 0);
    #500;
    
    // Test Case 5: Short ON with quick change attempt (should block)
    test_direction_change(5, 2, 5, 1);
    #500;
    
    // Test Case 6: Short ON with sufficient wait (should allow)
    test_direction_change(5, 7, 5, 1);
    #500;

    // SECTION 4: Mixed Frequency Tests
    $display("\n=== MIXED FREQUENCY TESTS ===");
    
    // Forward long to reverse short
    test_direction_change(30, 35, 5, 1);
    #500;
    
    // Reverse long to forward short
    test_direction_change(30, 35, 5, 0);
    #500;
    
    // Forward short to reverse long
    test_direction_change(5, 7, 30, 1);
    #500;
    
    // Reverse short to forward long
    test_direction_change(5, 7, 30, 0);
    #500;

    // SECTION 5: Rapid Alternation Tests
    $display("\n=== RAPID ALTERNATION TESTS ===");
    
    // Multiple short transitions with proper timing
    repeat(5) begin
        test_direction_change(5, 7, 5, 1);
        test_direction_change(5, 7, 5, 0);
    end

    // Multiple medium transitions with proper timing
    repeat(3) begin
        test_direction_change(15, 20, 15, 1);
        test_direction_change(15, 20, 15, 0);
    end

    $display("\n=== Test Complete ===");
    #100;
    $finish;
end

// Enhanced monitoring with debug signals
initial begin
    $monitor("Time=%0t rst_n=%b InVGSf=%b InVGSr=%b FWD_SET=%b REV_SET=%b LastDirFwd=%b FwdCnt=%d RevCnt=%d FlybackCnt=%d",
             $time, rst_n, InVGSf, InVGSr, TB_FWD_SET, TB_REV_SET,
             uut.last_dir_forward, uut.fwd_on_counter, uut.rev_on_counter, uut.flyback_counter);
end

endmodule

FPGA/hbridge_test.vcd
$date
	Wed Jan 15 14:19:53 2025
$end
$version
	Icarus Verilog
$end
$timescale
	100ps
$end
$scope module hbridge_controller_tb $end
$var wire 1 ! TB_FWD_SET $end
$var wire 1 " TB_REV_SET $end
$var wire 1 # Q4_out $end
$var wire 1 $ Q3_out $end
$var wire 1 % Q2_out $end
$var wire 1 & Q1_out $end
$var reg 1 ' InVGSf $end
$var reg 1 ( InVGSr $end
$var reg 1 ) clk $end
$var reg 1 * rst_n $end
$scope module uut $end
$var wire 1 ' InVGSf $end
$var wire 1 ( InVGSr $end
$var wire 1 ) clk $end
$var wire 1 * rst_n $end
$var reg 1 + FlybackVGS $end
$var reg 1 , OutVGSf $end
$var reg 1 - OutVGSr $end
$var reg 1 & Q1_out $end
$var reg 1 % Q2_out $end
$var reg 1 $ Q3_out $end
$var reg 1 # Q4_out $end
$var reg 1 . direction_blocked $end
$var reg 1 / falling_edge_detected $end
$var reg 16 0 flyback_counter [15:0] $end
$var reg 16 1 fwd_on_counter [15:0] $end
$var reg 1 2 in_flyback_mode $end
$var reg 1 3 last_dir_forward $end
$var reg 16 4 rev_on_counter [15:0] $end
$var reg 1 5 rising_edge_detected $end
$upscope $end
$scope task test_direction_change $end
$var integer 32 6 first_dir_cycles [31:0] $end
$var integer 32 7 second_dir_cycles [31:0] $end
$var integer 32 8 start_forward [31:0] $end
$var integer 32 9 wait_cycles [31:0] $end
$upscope $end
$scope task test_forward_pwm $end
$var integer 32 : off_cycles [31:0] $end
$var integer 32 ; on_cycles [31:0] $end
$var integer 32 < repeat_count [31:0] $end
$upscope $end
$scope task test_reverse_pwm $end
$var integer 32 = off_cycles [31:0] $end
$var integer 32 > on_cycles [31:0] $end
$var integer 32 ? repeat_count [31:0] $end
$upscope $end
$upscope $end
$enddefinitions $end
#0
$dumpvars
bx ?
bx >
bx =
bx <
bx ;
bx :
bx 9
bx 8
bx 7
bx 6
05
b0 4
03
02
b0 1
b0 0
0/
0.
0-
0,
1+
0*
0)
0(
0'
1&
0%
1$
0#
0"
0!
$end
#417
1)
#834
0)
#1000
1*
#1251
1)
#1668
0)
#2000
1'
b11 <
b11110 :
b11110 ;
#2085
0$
0&
15
0+
1)
#2502
1!
1#
1&
13
1,
0)
#2919
b1 1
1)
#3336
0)
#3753
b10 1
1)
#4170
0)
#4587
b11 1
1)
#5004
0)
#5421
b100 1
1)
#5838
0)
#6255
b101 1
1)
#6672
0)
#7089
b110 1
1)
#7506
0)
#7923
b111 1
1)
#8340
0)
#8757
b1000 1
1)
#9174
0)
#9591
b1001 1
1)
#10008
0)
#10425
b1010 1
1)
#10842
0)
#11259
b1011 1
1)
#11676
0)
#12093
b1100 1
1)
#12510
0)
#12927
b1101 1
1)
#13344
0)
#13761
b1110 1
1)
#14178
0)
#14595
b1111 1
1)
#15012
0)
#15429
b10000 1
1)
#15846
0)
#16263
b10001 1
1)
#16680
0)
#17097
b10010 1
1)
#17514
0)
#17931
b10011 1
1)
#18348
0)
#18765
b10100 1
1)
#19182
0)
#19599
b10101 1
1)
#20016
0)
#20433
b10110 1
1)
#20850
0)
#21267
b10111 1
1)
#21684
0)
#22101
b11000 1
1)
#22518
0)
#22935
b11001 1
1)
#23352
0)
#23769
b11010 1
1)
#24186
0)
#24603
b11011 1
1)
#25020
0)
#25437
b11100 1
1)
#25854
0)
#26271
1$
12
1/
1+
05
0'
1)
#26688
0!
0#
0,
0)
#27105
b11011 1
b1 0
1)
#27522
0)
#27939
b11010 1
b10 0
1)
#28356
0)
#28773
b11001 1
b11 0
1)
#29190
0)
#29607
b11000 1
b100 0
1)
#30024
0)
#30441
b10111 1
b101 0
1)
#30858
0)
#31275
b10110 1
b110 0
1)
#31692
0)
#32109
b10101 1
b111 0
1)
#32526
0)
#32943
b10100 1
b1000 0
1)
#33360
0)
#33777
b10011 1
b1001 0
1)
#34194
0)
#34611
b10010 1
b1010 0
1)
#35028
0)
#35445
b10001 1
b1011 0
1)
#35862
0)
#36279
b10000 1
b1100 0
1)
#36696
0)
#37113
b1111 1
b1101 0
1)
#37530
0)
#37947
b1110 1
b1110 0
1)
#38364
0)
#38781
b1101 1
b1111 0
1)
#39198
0)
#39615
b1100 1
b10000 0
1)
#40032
0)
#40449
b1011 1
b10001 0
1)
#40866
0)
#41283
b1010 1
b10010 0
1)
#41700
0)
#42117
b1001 1
b10011 0
1)
#42534
0)
#42951
b1000 1
b10100 0
1)
#43368
0)
#43785
b111 1
b10101 0
1)
#44202
0)
#44619
b110 1
b10110 0
1)
#45036
0)
#45453
b101 1
b10111 0
1)
#45870
0)
#46287
b100 1
b11000 0
1)
#46704
0)
#47121
b11 1
b11001 0
1)
#47538
0)
#47955
b10 1
b11010 0
1)
#48372
0)
#48789
b1 1
b11011 0
1)
#49206
0)
#49623
02
b0 1
b0 0
1)
#50040
0)
#50457
1)
#50874
0)
#51291
0$
0&
0/
15
0+
1'
1)
#51708
1!
1#
1&
1,
0)
#52125
b1 1
1)
#52542
0)
#52959
b10 1
1)
#53376
0)
#53793
b11 1
1)
#54210
0)
#54627
b100 1
1)
#55044
0)
#55461
b101 1
1)
#55878
0)
#56295
b110 1
1)
#56712
0)
#57129
b111 1
1)
#57546
0)
#57963
b1000 1
1)
#58380
0)
#58797
b1001 1
1)
#59214
0)
#59631
b1010 1
1)
#60048
0)
#60465
b1011 1
1)
#60882
0)
#61299
b1100 1
1)
#61716
0)
#62133
b1101 1
1)
#62550
0)
#62967
b1110 1
1)
#63384
0)
#63801
b1111 1
1)
#64218
0)
#64635
b10000 1
1)
#65052
0)
#65469
b10001 1
1)
#65886
0)
#66303
b10010 1
1)
#66720
0)
#67137
b10011 1
1)
#67554
0)
#67971
b10100 1
1)
#68388
0)
#68805
b10101 1
1)
#69222
0)
#69639
b10110 1
1)
#70056
0)
#70473
b10111 1
1)
#70890
0)
#71307
b11000 1
1)
#71724
0)
#72141
b11001 1
1)
#72558
0)
#72975
b11010 1
1)
#73392
0)
#73809
b11011 1
1)
#74226
0)
#74643
b11100 1
1)
#75060
0)
#75477
b11101 1
1)
#75894
0)
#76311
1$
12
1/
1+
05
0'
1)
#76728
0!
0#
0,
0)
#77145
b11100 1
b1 0
1)
#77562
0)
#77979
b11011 1
b10 0
1)
#78396
0)
#78813
b11010 1
b11 0
1)
#79230
0)
#79647
b11001 1
b100 0
1)
#80064
0)
#80481
b11000 1
b101 0
1)
#80898
0)
#81315
b10111 1
b110 0
1)
#81732
0)
#82149
b10110 1
b111 0
1)
#82566
0)
#82983
b10101 1
b1000 0
1)
#83400
0)
#83817
b10100 1
b1001 0
1)
#84234
0)
#84651
b10011 1
b1010 0
1)
#85068
0)
#85485
b10010 1
b1011 0
1)
#85902
0)
#86319
b10001 1
b1100 0
1)
#86736
0)
#87153
b10000 1
b1101 0
1)
#87570
0)
#87987
b1111 1
b1110 0
1)
#88404
0)
#88821
b1110 1
b1111 0
1)
#89238
0)
#89655
b1101 1
b10000 0
1)
#90072
0)
#90489
b1100 1
b10001 0
1)
#90906
0)
#91323
b1011 1
b10010 0
1)
#91740
0)
#92157
b1010 1
b10011 0
1)
#92574
0)
#92991
b1001 1
b10100 0
1)
#93408
0)
#93825
b1000 1
b10101 0
1)
#94242
0)
#94659
b111 1
b10110 0
1)
#95076
0)
#95493
b110 1
b10111 0
1)
#95910
0)
#96327
b101 1
b11000 0
1)
#96744
0)
#97161
b100 1
b11001 0
1)
#97578
0)
#97995
b11 1
b11010 0
1)
#98412
0)
#98829
b10 1
b11011 0
1)
#99246
0)
#99663
b1 1
b11100 0
1)
#100080
0)
#100497
02
b0 1
b0 0
1)
#100914
0)
#101331
0$
0&
0/
15
0+
1'
1)
#101748
1!
1#
1&
1,
0)
#102165
b1 1
1)
#102582
0)
#102999
b10 1
1)
#103416
0)
#103833
b11 1
1)
#104250
0)
#104667
b100 1
1)
#105084
0)
#105501
b101 1
1)
#105918
0)
#106335
b110 1
1)
#106752
0)
#107169
b111 1
1)
#107586
0)
#108003
b1000 1
1)
#108420
0)
#108837
b1001 1
1)
#109254
0)
#109671
b1010 1
1)
#110088
0)
#110505
b1011 1
1)
#110922
0)
#111339
b1100 1
1)
#111756
0)
#112173
b1101 1
1)
#112590
0)
#113007
b1110 1
1)
#113424
0)
#113841
b1111 1
1)
#114258
0)
#114675
b10000 1
1)
#115092
0)
#115509
b10001 1
1)
#115926
0)
#116343
b10010 1
1)
#116760
0)
#117177
b10011 1
1)
#117594
0)
#118011
b10100 1
1)
#118428
0)
#118845
b10101 1
1)
#119262
0)
#119679
b10110 1
1)
#120096
0)
#120513
b10111 1
1)
#120930
0)
#121347
b11000 1
1)
#121764
0)
#122181
b11001 1
1)
#122598
0)
#123015
b11010 1
1)
#123432
0)
#123849
b11011 1
1)
#124266
0)
#124683
b11100 1
1)
#125100
0)
#125517
b11101 1
1)
#125934
0)
#126351
1$
12
1/
1+
05
0'
1)
#126768
0!
0#
0,
0)
#127185
b11100 1
b1 0
1)
#127602
0)
#128019
b11011 1
b10 0
1)
#128436
0)
#128853
b11010 1
b11 0
1)
#129270
0)
#129687
b11001 1
b100 0
1)
#130104
0)
#130521
b11000 1
b101 0
1)
#130938
0)
#131355
b10111 1
b110 0
1)
#131772
0)
#132189
b10110 1
b111 0
1)
#132606
0)
#133023
b10101 1
b1000 0
1)
#133440
0)
#133857
b10100 1
b1001 0
1)
#134274
0)
#134691
b10011 1
b1010 0
1)
#135108
0)
#135525
b10010 1
b1011 0
1)
#135942
0)
#136359
b10001 1
b1100 0
1)
#136776
0)
#137193
b10000 1
b1101 0
1)
#137610
0)
#138027
b1111 1
b1110 0
1)
#138444
0)
#138861
b1110 1
b1111 0
1)
#139278
0)
#139695
b1101 1
b10000 0
1)
#140112
0)
#140529
b1100 1
b10001 0
1)
#140946
0)
#141363
b1011 1
b10010 0
1)
#141780
0)
#142197
b1010 1
b10011 0
1)
#142614
0)
#143031
b1001 1
b10100 0
1)
#143448
0)
#143865
b1000 1
b10101 0
1)
#144282
0)
#144699
b111 1
b10110 0
1)
#145116
0)
#145533
b110 1
b10111 0
1)
#145950
0)
#146367
b101 1
b11000 0
1)
#146784
0)
#147201
b100 1
b11001 0
1)
#147618
0)
#148035
b11 1
b11010 0
1)
#148452
0)
#148869
b10 1
b11011 0
1)
#149286
0)
#149703
b1 1
b11100 0
1)
#150120
0)
#150537
02
b0 1
b0 0
1)
#150954
0)
#151371
1)
#151788
0)
#152205
1)
#152622
0)
#153039
1)
#153371
1'
b101 <
b1111 :
b1111 ;
#153456
0)
#153873
0$
0&
0/
15
0+
1)
#154290
1!
1#
1&
1,
0)
#154707
b1 1
1)
#155124
0)
#155541
b10 1
1)
#155958
0)
#156375
b11 1
1)
#156792
0)
#157209
b100 1
1)
#157626
0)
#158043
b101 1
1)
#158460
0)
#158877
b110 1
1)
#159294
0)
#159711
b111 1
1)
#160128
0)
#160545
b1000 1
1)
#160962
0)
#161379
b1001 1
1)
#161796
0)
#162213
b1010 1
1)
#162630
0)
#163047
b1011 1
1)
#163464
0)
#163881
b1100 1
1)
#164298
0)
#164715
b1101 1
1)
#165132
0)
#165549
1$
12
1/
1+
05
0'
1)
#165966
0!
0#
0,
0)
#166383
b1100 1
b1 0
1)
#166800
0)
#167217
b1011 1
b10 0
1)
#167634
0)
#168051
b1010 1
b11 0
1)
#168468
0)
#168885
b1001 1
b100 0
1)
#169302
0)
#169719
b1000 1
b101 0
1)
#170136
0)
#170553
b111 1
b110 0
1)
#170970
0)
#171387
b110 1
b111 0
1)
#171804
0)
#172221
b101 1
b1000 0
1)
#172638
0)
#173055
b100 1
b1001 0
1)
#173472
0)
#173889
b11 1
b1010 0
1)
#174306
0)
#174723
b10 1
b1011 0
1)
#175140
0)
#175557
b1 1
b1100 0
1)
#175974
0)
#176391
02
b0 1
b0 0
1)
#176808
0)
#177225
1)
#177642
0)
#178059
0$
0&
0/
15
0+
1'
1)
#178476
1!
1#
1&
1,
0)
#178893
b1 1
1)
#179310
0)
#179727
b10 1
1)
#180144
0)
#180561
b11 1
1)
#180978
0)
#181395
b100 1
1)
#181812
0)
#182229
b101 1
1)
#182646
0)
#183063
b110 1
1)
#183480
0)
#183897
b111 1
1)
#184314
0)
#184731
b1000 1
1)
#185148
0)
#185565
b1001 1
1)
#185982
0)
#186399
b1010 1
1)
#186816
0)
#187233
b1011 1
1)
#187650
0)
#188067
b1100 1
1)
#188484
0)
#188901
b1101 1
1)
#189318
0)
#189735
b1110 1
1)
#190152
0)
#190569
1$
12
1/
1+
05
0'
1)
#190986
0!
0#
0,
0)
#191403
b1101 1
b1 0
1)
#191820
0)
#192237
b1100 1
b10 0
1)
#192654
0)
#193071
b1011 1
b11 0
1)
#193488
0)
#193905
b1010 1
b100 0
1)
#194322
0)
#194739
b1001 1
b101 0
1)
#195156
0)
#195573
b1000 1
b110 0
1)
#195990
0)
#196407
b111 1
b111 0
1)
#196824
0)
#197241
b110 1
b1000 0
1)
#197658
0)
#198075
b101 1
b1001 0
1)
#198492
0)
#198909
b100 1
b1010 0
1)
#199326
0)
#199743
b11 1
b1011 0
1)
#200160
0)
#200577
b10 1
b1100 0
1)
#200994
0)
#201411
b1 1
b1101 0
1)
#201828
0)
#202245
02
b0 1
b0 0
1)
#202662
0)
#203079
0$
0&
0/
15
0+
1'
1)
#203496
1!
1#
1&
1,
0)
#203913
b1 1
1)
#204330
0)
#204747
b10 1
1)
#205164
0)
#205581
b11 1
1)
#205998
0)
#206415
b100 1
1)
#206832
0)
#207249
b101 1
1)
#207666
0)
#208083
b110 1
1)
#208500
0)
#208917
b111 1
1)
#209334
0)
#209751
b1000 1
1)
#210168
0)
#210585
b1001 1
1)
#211002
0)
#211419
b1010 1
1)
#211836
0)
#212253
b1011 1
1)
#212670
0)
#213087
b1100 1
1)
#213504
0)
#213921
b1101 1
1)
#214338
0)
#214755
b1110 1
1)
#215172
0)
#215589
1$
12
1/
1+
05
0'
1)
#216006
0!
0#
0,
0)
#216423
b1101 1
b1 0
1)
#216840
0)
#217257
b1100 1
b10 0
1)
#217674
0)
#218091
b1011 1
b11 0
1)
#218508
0)
#218925
b1010 1
b100 0
1)
#219342
0)
#219759
b1001 1
b101 0
1)
#220176
0)
#220593
b1000 1
b110 0
1)
#221010
0)
#221427
b111 1
b111 0
1)
#221844
0)
#222261
b110 1
b1000 0
1)
#222678
0)
#223095
b101 1
b1001 0
1)
#223512
0)
#223929
b100 1
b1010 0
1)
#224346
0)
#224763
b11 1
b1011 0
1)
#225180
0)
#225597
b10 1
b1100 0
1)
#226014
0)
#226431
b1 1
b1101 0
1)
#226848
0)
#227265
02
b0 1
b0 0
1)
#227682
0)
#228099
0$
0&
0/
15
0+
1'
1)
#228516
1!
1#
1&
1,
0)
#228933
b1 1
1)
#229350
0)
#229767
b10 1
1)
#230184
0)
#230601
b11 1
1)
#231018
0)
#231435
b100 1
1)
#231852
0)
#232269
b101 1
1)
#232686
0)
#233103
b110 1
1)
#233520
0)
#233937
b111 1
1)
#234354
0)
#234771
b1000 1
1)
#235188
0)
#235605
b1001 1
1)
#236022
0)
#236439
b1010 1
1)
#236856
0)
#237273
b1011 1
1)
#237690
0)
#238107
b1100 1
1)
#238524
0)
#238941
b1101 1
1)
#239358
0)
#239775
b1110 1
1)
#240192
0)
#240609
1$
12
1/
1+
05
0'
1)
#241026
0!
0#
0,
0)
#241443
b1101 1
b1 0
1)
#241860
0)
#242277
b1100 1
b10 0
1)
#242694
0)
#243111
b1011 1
b11 0
1)
#243528
0)
#243945
b1010 1
b100 0
1)
#244362
0)
#244779
b1001 1
b101 0
1)
#245196
0)
#245613
b1000 1
b110 0
1)
#246030
0)
#246447
b111 1
b111 0
1)
#246864
0)
#247281
b110 1
b1000 0
1)
#247698
0)
#248115
b101 1
b1001 0
1)
#248532
0)
#248949
b100 1
b1010 0
1)
#249366
0)
#249783
b11 1
b1011 0
1)
#250200
0)
#250617
b10 1
b1100 0
1)
#251034
0)
#251451
b1 1
b1101 0
1)
#251868
0)
#252285
02
b0 1
b0 0
1)
#252702
0)
#253119
0$
0&
0/
15
0+
1'
1)
#253536
1!
1#
1&
1,
0)
#253953
b1 1
1)
#254370
0)
#254787
b10 1
1)
#255204
0)
#255621
b11 1
1)
#256038
0)
#256455
b100 1
1)
#256872
0)
#257289
b101 1
1)
#257706
0)
#258123
b110 1
1)
#258540
0)
#258957
b111 1
1)
#259374
0)
#259791
b1000 1
1)
#260208
0)
#260625
b1001 1
1)
#261042
0)
#261459
b1010 1
1)
#261876
0)
#262293
b1011 1
1)
#262710
0)
#263127
b1100 1
1)
#263544
0)
#263961
b1101 1
1)
#264378
0)
#264795
b1110 1
1)
#265212
0)
#265629
1$
12
1/
1+
05
0'
1)
#266046
0!
0#
0,
0)
#266463
b1101 1
b1 0
1)
#266880
0)
#267297
b1100 1
b10 0
1)
#267714
0)
#268131
b1011 1
b11 0
1)
#268548
0)
#268965
b1010 1
b100 0
1)
#269382
0)
#269799
b1001 1
b101 0
1)
#270216
0)
#270633
b1000 1
b110 0
1)
#271050
0)
#271467
b111 1
b111 0
1)
#271884
0)
#272301
b110 1
b1000 0
1)
#272718
0)
#273135
b101 1
b1001 0
1)
#273552
0)
#273969
b100 1
b1010 0
1)
#274386
0)
#274803
b11 1
b1011 0
1)
#275220
0)
#275637
b10 1
b1100 0
1)
#276054
0)
#276471
b1 1
b1101 0
1)
#276888
0)
#277305
02
b0 1
b0 0
1)
#277722
0)
#278139
1)
#278556
0)
#278973
1)
#279390
0)
#279807
1)
#280139
1'
b1010 <
b101 :
b101 ;
#280224
0)
#280641
0$
0&
0/
15
0+
1)
#281058
1!
1#
1&
1,
0)
#281475
b1 1
1)
#281892
0)
#282309
b10 1
1)
#282726
0)
#283143
b11 1
1)
#283560
0)
#283977
1$
12
1/
1+
05
0'
1)
#284394
0!
0#
0,
0)
#284811
b10 1
b1 0
1)
#285228
0)
#285645
b1 1
b10 0
1)
#286062
0)
